odoo/addons/photovoltaic_products/__init__.py
odoo/addons/photovoltaic_products/__manifest__.py
odoo/addons/photovoltaic_products/i18n/es.po
odoo/addons/photovoltaic_products/i18n/photovoltaic_products.pot
odoo/addons/photovoltaic_products/models/__init__.py
odoo/addons/photovoltaic_products/models/photovoltaic_inverter.py
odoo/addons/photovoltaic_products/models/photovoltaic_module.py
odoo/addons/photovoltaic_products/models/product_template.py
odoo/addons/photovoltaic_products/models/res_config_settings.py
odoo/addons/photovoltaic_products/security/ir.model.access.csv
odoo/addons/photovoltaic_products/views/photovoltaic_inverter.xml
odoo/addons/photovoltaic_products/views/photovoltaic_module.xml
odoo/addons/photovoltaic_products/views/product_template.xml
odoo13_addon_photovoltaic_products-13.0.0.0.3.dist-info/METADATA
odoo13_addon_photovoltaic_products-13.0.0.0.3.dist-info/WHEEL
odoo13_addon_photovoltaic_products-13.0.0.0.3.dist-info/top_level.txt
odoo13_addon_photovoltaic_products-13.0.0.0.3.dist-info/RECORD
